directoryhandler.py
directoryhandler-0.2.0.dist-info/LICENSE
directoryhandler-0.2.0.dist-info/METADATA
directoryhandler-0.2.0.dist-info/WHEEL
directoryhandler-0.2.0.dist-info/top_level.txt
directoryhandler-0.2.0.dist-info/RECORD
