Metadata-Version: 2.1
Name: directoryhandler
Version: 0.2.0
Summary: Local directory lookup and management
Home-page: UNKNOWN
Author: UNKNOWN
Author-email: UNKNOWN
License: UNKNOWN
Platform: UNKNOWN
Requires-Dist: lxml
Requires-Dist: jsondatahelper
